examples/__init__.py
examples/authentication.py
examples/basic_usage.py
examples/batch_download.py
examples/download_episode.py
examples/json_export.py
examples/seasons_and_arcs.py
jut_su_py-0.1.5.dist-info/licenses/LICENSE
jutsu_scraper/__init__.py
jutsu_scraper/client.py
jutsu_scraper/constants.py
jutsu_scraper/downloader.py
jutsu_scraper/exceptions.py
jutsu_scraper/logger.py
jutsu_scraper/parser.py
jutsu_scraper/types.py
jutsu_scraper/utils.py
jutsu_scraper/video_extractor.py
jutsu_scraper/models/__init__.py
jutsu_scraper/models/anime.py
jutsu_scraper/models/arc.py
jutsu_scraper/models/episode.py
jutsu_scraper/models/rating.py
jutsu_scraper/models/season.py
jut_su_py-0.1.5.dist-info/METADATA
jut_su_py-0.1.5.dist-info/WHEEL
jut_su_py-0.1.5.dist-info/top_level.txt
jut_su_py-0.1.5.dist-info/RECORD
